README.rst
gy.py
setup.py
gy.egg-info/PKG-INFO
gy.egg-info/SOURCES.txt
gy.egg-info/dependency_links.txt
gy.egg-info/entry_points.txt
gy.egg-info/not-zip-safe
gy.egg-info/requires.txt
gy.egg-info/top_level.txt